provbook/__init__.py
provbook/_version.py
provbook/notebook_ext/ProvBook1.png
provbook/notebook_ext/ProvBook2.png
provbook/notebook_ext/ProvBook3.png
provbook/notebook_ext/ProvBookDiff1.png
provbook/notebook_ext/ProvBookDiff2.png
provbook/notebook_ext/icon.png
provbook/notebook_ext/index.js
provbook/notebook_ext/notebook_rdf.png
provbook/notebook_ext/provbook.css
provbook/notebook_ext/provbook.yaml
provbook/notebook_ext/readme.md
provbook/notebook_rdf/__init__.py
provbook/notebook_rdf/__main__.py
provbook/notebook_rdf/nb2rdf.py
provbook/notebook_rdf/rdf2nb.py
provbook/webapp/__init__.py
provbook/webapp/nb_server_extension.py
provbook/webapp/nbdimeserver.py
provbook/webapp/static/1.provbookdiff.js
provbook/webapp/static/1.provbookdiff.js.map
provbook/webapp/static/2.provbookdiff.js
provbook/webapp/static/2.provbookdiff.js.map
provbook/webapp/static/43bb4cbf1d0ecfdb1309e4cb67264f35.ttf
provbook/webapp/static/5a0856eb52623ae94b09dbbf31a27b95.ttf
provbook/webapp/static/provbookdiff.js
provbook/webapp/static/provbookdiff.js.map
provbook/webapp/templates/provbookdiff.html
provbook/webapp/templates/provbookpage.html
provbook-1.1.0.data/data/etc/jupyter/jupyter_notebook_config.d/provbook.json
provbook-1.1.0.data/data/etc/jupyter/nbconfig/notebook.d/provbook.json
provbook-1.1.0.data/data/share/jupyter/nbextensions/provbook/ProvBook1.png
provbook-1.1.0.data/data/share/jupyter/nbextensions/provbook/ProvBook2.png
provbook-1.1.0.data/data/share/jupyter/nbextensions/provbook/ProvBook3.png
provbook-1.1.0.data/data/share/jupyter/nbextensions/provbook/ProvBookDiff1.png
provbook-1.1.0.data/data/share/jupyter/nbextensions/provbook/ProvBookDiff2.png
provbook-1.1.0.data/data/share/jupyter/nbextensions/provbook/icon.png
provbook-1.1.0.data/data/share/jupyter/nbextensions/provbook/index.js
provbook-1.1.0.data/data/share/jupyter/nbextensions/provbook/notebook_rdf.png
provbook-1.1.0.data/data/share/jupyter/nbextensions/provbook/provbook.css
provbook-1.1.0.dist-info/LICENSE.md
provbook-1.1.0.dist-info/METADATA
provbook-1.1.0.dist-info/WHEEL
provbook-1.1.0.dist-info/entry_points.txt
provbook-1.1.0.dist-info/top_level.txt
provbook-1.1.0.dist-info/RECORD
