Metadata-Version: 2.1
Name: provbook
Version: 1.1.0
Summary: Provenance and differencing of the Jupyter Notebook Execution
Home-page: https://github.com/Sheeba-Samuel/
Author: Sheeba Samuel
Author-email: sheeba.samuel@uni-jena.de
License: BSD
Keywords: Interactive,Provenance,Reproducibility,RDF,Jupyter
Platform: Linux
Platform: Mac OS X
Platform: Windows
Classifier: Intended Audience :: Developers
Classifier: Intended Audience :: Science/Research
Classifier: Intended Audience :: System Administrators
Classifier: License :: OSI Approved :: BSD License
Classifier: Programming Language :: Python
Classifier: Programming Language :: Python :: 2.7
Classifier: Programming Language :: Python :: 3
Classifier: Programming Language :: Python :: 3.3
Classifier: Programming Language :: Python :: 3.4
Classifier: Programming Language :: Python :: 3.5
Classifier: Programming Language :: Python :: 3.6
Classifier: Framework :: Jupyter
Requires-Python: >=2.7,!=3.0.*,!=3.1.*,!=3.2.*,!=3.3.*
License-File: LICENSE.md
Requires-Dist: nbformat
Requires-Dist: six
Requires-Dist: colorama
Requires-Dist: tornado
Requires-Dist: requests
Requires-Dist: GitPython (!=2.1.4,!=2.1.5,!=2.1.6)
Requires-Dist: notebook
Requires-Dist: jinja2 (>=2.9)
Requires-Dist: jupyter
Requires-Dist: nbdime
Requires-Dist: rdflib
Requires-Dist: backports.shutil-which ; python_version == "2.7"
Requires-Dist: backports.functools-lru-cache ; python_version == "2.7"
Provides-Extra: docs
Requires-Dist: sphinx ; extra == 'docs'
Requires-Dist: recommonmark ; extra == 'docs'
Requires-Dist: sphinx-rtd-theme ; extra == 'docs'
